interactivenet/__init__.py
interactivenet/deploy/__init__.py
interactivenet/deploy/download_model.py
interactivenet/deploy/save_model.py
interactivenet/experiment_planning/__init__.py
interactivenet/experiment_planning/fingerprinting.py
interactivenet/experiment_planning/generate_dataset_json.py
interactivenet/experiment_planning/mimic_annotations.py
interactivenet/experiment_planning/plan_and_process.py
interactivenet/experiment_planning/preprocessing.py
interactivenet/networks/__init__.py
interactivenet/networks/unet.py
interactivenet/test/__init__.py
interactivenet/test/ensemble.py
interactivenet/test/inference.py
interactivenet/test/predict.py
interactivenet/test/refinement.py
interactivenet/test/run.py
interactivenet/training/__init__.py
interactivenet/training/postprocessing.py
interactivenet/training/run.py
interactivenet/transforms/__init__.py
interactivenet/transforms/set_transforms.py
interactivenet/transforms/transforms.py
interactivenet/utils/__init__.py
interactivenet/utils/callbacks.py
interactivenet/utils/dump.py
interactivenet/utils/jsonencoders.py
interactivenet/utils/mlflow.py
interactivenet/utils/postprocessing.py
interactivenet/utils/resample.py
interactivenet/utils/results.py
interactivenet/utils/statistics.py
interactivenet/utils/subtypes.py
interactivenet/utils/utils.py
interactivenet/utils/visualize.py
interactivenet-0.2.1.dist-info/LICENSE
interactivenet-0.2.1.dist-info/METADATA
interactivenet-0.2.1.dist-info/WHEEL
interactivenet-0.2.1.dist-info/entry_points.txt
interactivenet-0.2.1.dist-info/top_level.txt
interactivenet-0.2.1.dist-info/RECORD
